dbt_artifacts_parser/__init__.py
dbt_artifacts_parser/parser.py
dbt_artifacts_parser/utils.py
dbt_artifacts_parser/parsers/__init__.py
dbt_artifacts_parser/parsers/base.py
dbt_artifacts_parser/parsers/utils.py
dbt_artifacts_parser/parsers/version_map.py
dbt_artifacts_parser/parsers/catalog/__init__.py
dbt_artifacts_parser/parsers/catalog/catalog_v1.py
dbt_artifacts_parser/parsers/manifest/__init__.py
dbt_artifacts_parser/parsers/manifest/manifest_v1.py
dbt_artifacts_parser/parsers/manifest/manifest_v10.py
dbt_artifacts_parser/parsers/manifest/manifest_v11.py
dbt_artifacts_parser/parsers/manifest/manifest_v12.py
dbt_artifacts_parser/parsers/manifest/manifest_v2.py
dbt_artifacts_parser/parsers/manifest/manifest_v3.py
dbt_artifacts_parser/parsers/manifest/manifest_v4.py
dbt_artifacts_parser/parsers/manifest/manifest_v5.py
dbt_artifacts_parser/parsers/manifest/manifest_v6.py
dbt_artifacts_parser/parsers/manifest/manifest_v7.py
dbt_artifacts_parser/parsers/manifest/manifest_v8.py
dbt_artifacts_parser/parsers/manifest/manifest_v9.py
dbt_artifacts_parser/parsers/run_results/__init__.py
dbt_artifacts_parser/parsers/run_results/run_results_v1.py
dbt_artifacts_parser/parsers/run_results/run_results_v2.py
dbt_artifacts_parser/parsers/run_results/run_results_v3.py
dbt_artifacts_parser/parsers/run_results/run_results_v4.py
dbt_artifacts_parser/parsers/run_results/run_results_v5.py
dbt_artifacts_parser/parsers/run_results/run_results_v6.py
dbt_artifacts_parser/parsers/sources/__init__.py
dbt_artifacts_parser/parsers/sources/sources_v1.py
dbt_artifacts_parser/parsers/sources/sources_v2.py
dbt_artifacts_parser/parsers/sources/sources_v3.py
dbt_artifacts_parser/resources/catalog/catalog_v1.json
dbt_artifacts_parser/resources/manifest/manifest_v1.json
dbt_artifacts_parser/resources/manifest/manifest_v10.json
dbt_artifacts_parser/resources/manifest/manifest_v11.json
dbt_artifacts_parser/resources/manifest/manifest_v12.json
dbt_artifacts_parser/resources/manifest/manifest_v2.json
dbt_artifacts_parser-0.11.0.dist-info/METADATA
dbt_artifacts_parser-0.11.0.dist-info/WHEEL
dbt_artifacts_parser-0.11.0.dist-info/licenses/LICENSE
dbt_artifacts_parser-0.11.0.dist-info/RECORD
