Metadata-Version: 2.4
Name: dbt-artifacts-parser
Version: 0.11.0
Summary: A dbt artifacts parser in python
Project-URL: Home, https://github.com/yu-iskw/dbt-artifacts-parser
Author: yu-iskw
License:                                  Apache License
License-File: LICENSE
Classifier: Development Status :: 4 - Beta
Classifier: Intended Audience :: Information Technology
Classifier: Intended Audience :: System Administrators
Classifier: License :: OSI Approved :: Apache Software License
Classifier: Operating System :: OS Independent
Classifier: Programming Language :: Python
Classifier: Programming Language :: Python :: 3
Classifier: Programming Language :: Python :: 3 :: Only
Classifier: Programming Language :: Python :: 3.9
Classifier: Programming Language :: Python :: 3.10
Classifier: Programming Language :: Python :: 3.11
Classifier: Programming Language :: Python :: 3.12
Classifier: Programming Language :: Python :: 3.13
Classifier: Topic :: Software Development :: Libraries
Classifier: Topic :: Software Development :: Libraries :: Python Modules
Classifier: Typing :: Typed
Requires-Python: >=3.9.0
Requires-Dist: pydantic<3.0,>=2.0
Provides-Extra: dev
Requires-Dist: black>=25.9.0; extra == 'dev'
Requires-Dist: build>=1.3.0; extra == 'dev'
Requires-Dist: datamodel-code-generator>=0.35.0; extra == 'dev'
Requires-Dist: flake8>=7.3.0; extra == 'dev'
Requires-Dist: isort>=6.1.0; extra == 'dev'
Requires-Dist: mypy>=1.18.2; extra == 'dev'
Requires-Dist: pdoc3>=0.11.6; extra == 'dev'
Requires-Dist: pre-commit>=4.3.0; extra == 'dev'
Requires-Dist: pylint>=3.3.9; extra == 'dev'
Requires-Dist: pytest>=8.4.2; extra == 'dev'
Requires-Dist: pyyaml>=6.0.3; extra == 'dev'
